deutschland/DashboardDeutschland/__init__.py
deutschland/DashboardDeutschland/api/__init__.py
deutschland/DashboardDeutschland/api/geo_api.py
deutschland/DashboardDeutschland/api/get_api.py
deutschland/DashboardDeutschland/api/indicators_api.py
deutschland/DashboardDeutschland/api_client.py
deutschland/DashboardDeutschland/apis/__init__.py
deutschland/DashboardDeutschland/configuration.py
deutschland/DashboardDeutschland/exceptions.py
deutschland/DashboardDeutschland/model/__init__.py
deutschland/DashboardDeutschland/model/geo.py
deutschland/DashboardDeutschland/model/geo_crs.py
deutschland/DashboardDeutschland/model/geo_crs_properties.py
deutschland/DashboardDeutschland/model/get.py
deutschland/DashboardDeutschland/model/get_category.py
deutschland/DashboardDeutschland/model/get_layout_tiles.py
deutschland/DashboardDeutschland/model/indicators.py
deutschland/DashboardDeutschland/model_utils.py
deutschland/DashboardDeutschland/models/__init__.py
deutschland/DashboardDeutschland/rest.py
de_dashboarddeutschland-0.1.0.dist-info/WHEEL
de_dashboarddeutschland-0.1.0.dist-info/METADATA
de_dashboarddeutschland-0.1.0.dist-info/RECORD
